{
  "@context": [
    "http://iiif.io/api/extension/navplace/context.json",
    "http://iiif.io/api/presentation/3/context.json"
  ],
  "id": "https://amsterdamtimemachine.github.io/datasprint-toekomsttiendaagse-2025/iiif/nha/2154567f-fd6e-b232-3390-bf19aea349dd.json",
  "type": "Manifest",
  "label": {
    "nl": [
      "Afscheid heer Bouwmans, adjudant van het Korps Rijkspolitie, AVD steunpunt Badhoevedorp. (1991-02-26)"
    ]
  },
  "metadata": [
    {
      "label": {
        "nl": [
          "Titel"
        ]
      },
      "value": {
        "nl": [
          "Afscheid heer Bouwmans, adjudant van het Korps Rijkspolitie, AVD steunpunt Badhoevedorp."
        ]
      }
    },
    {
      "label": {
        "nl": [
          "Datum"
        ]
      },
      "value": {
        "nl": [
          "1991-02-26"
        ]
      }
    },
    {
      "label": {
        "nl": [
          "Plaats"
        ]
      },
      "value": {
        "nl": [
          "<a href=\"http://www.wikidata.org/entity/Q568337\">Badhoevedorp</a>"
        ]
      }
    },
    {
      "label": {
        "nl": [
          "Concept"
        ]
      },
      "value": {
        "nl": [
          ""
        ]
      }
    },
    {
      "label": {
        "nl": [
          "GTAA"
        ]
      },
      "value": {
        "nl": [
          ""
        ]
      }
    }
  ],
  "navPlace": {
    "type": "FeatureCollection",
    "features": [
      {
        "type": "Feature",
        "geometry": {
          "type": "Point",
          "coordinates": [
            4.7803,
            52.3381
          ]
        },
        "properties": {
          "title": "Badhoevedorp",
          "url": "http://www.wikidata.org/entity/Q568337"
        }
      }
    ]
  },
  "items": [
    {
      "id": "https://amsterdamtimemachine.github.io/datasprint-toekomsttiendaagse-2025/iiif/2154567f-fd6e-b232-3390-bf19aea349dd/NL-HlmNHA_1478_33848K00_39/canvas",
      "type": "Canvas",
      "label": {
        "nl": [
          "Afscheid heer Bouwmans, adjudant van het Korps Rijkspolitie, AVD steunpunt Badhoevedorp."
        ]
      },
      "height": 4640,
      "width": 6049,
      "metadata": [
        {
          "label": {
            "nl": [
              "URI (Beeldbank)"
            ]
          },
          "value": {
            "nl": [
              "<a href=\"https://hdl.handle.net/21.12102/27bab094-60b6-6621-653f-e27c7a029a9a\">https://hdl.handle.net/21.12102/27bab094-60b6-6621-653f-e27c7a029a9a</a>"
            ]
          }
        }
      ],
      "items": [
        {
          "id": "https://amsterdamtimemachine.github.io/datasprint-toekomsttiendaagse-2025/iiif/2154567f-fd6e-b232-3390-bf19aea349dd/NL-HlmNHA_1478_33848K00_39/canvas/p0/page",
          "type": "AnnotationPage",
          "items": [
            {
              "id": "https://amsterdamtimemachine.github.io/datasprint-toekomsttiendaagse-2025/iiif/2154567f-fd6e-b232-3390-bf19aea349dd/NL-HlmNHA_1478_33848K00_39/canvas/p0/page/anno",
              "type": "Annotation",
              "motivation": "painting",
              "body": {
                "id": "https://maior-images.memorix.nl/ranh/iiif/5453f595-378b-b682-e4c3-d5944e21dff6/full/full/0/default.jpg",
                "type": "Image",
                "height": 4640,
                "width": 6049,
                "service": [
                  {
                    "@id": "https://maior-images.memorix.nl/ranh/iiif/5453f595-378b-b682-e4c3-d5944e21dff6",
                    "@type": "ImageService2",
                    "profile": "http://iiif.io/api/image/2/level2.json"
                  }
                ],
                "format": "image/jpeg"
              },
              "target": "https://amsterdamtimemachine.github.io/datasprint-toekomsttiendaagse-2025/iiif/2154567f-fd6e-b232-3390-bf19aea349dd/NL-HlmNHA_1478_33848K00_39/canvas"
            }
          ]
        }
      ]
    },
    {
      "id": "https://amsterdamtimemachine.github.io/datasprint-toekomsttiendaagse-2025/iiif/2154567f-fd6e-b232-3390-bf19aea349dd/NL-HlmNHA_1478_33848K00_37/canvas",
      "type": "Canvas",
      "label": {
        "nl": [
          "Afscheid heer Bouwmans, adjudant van het Korps Rijkspolitie, AVD steunpunt Badhoevedorp."
        ]
      },
      "height": 4640,
      "width": 6049,
      "metadata": [
        {
          "label": {
            "nl": [
              "URI (Beeldbank)"
            ]
          },
          "value": {
            "nl": [
              "<a href=\"https://hdl.handle.net/21.12102/34cd4aff-ff04-fb09-9bfa-f2ec8b190009\">https://hdl.handle.net/21.12102/34cd4aff-ff04-fb09-9bfa-f2ec8b190009</a>"
            ]
          }
        }
      ],
      "items": [
        {
          "id": "https://amsterdamtimemachine.github.io/datasprint-toekomsttiendaagse-2025/iiif/2154567f-fd6e-b232-3390-bf19aea349dd/NL-HlmNHA_1478_33848K00_37/canvas/p0/page",
          "type": "AnnotationPage",
          "items": [
            {
              "id": "https://amsterdamtimemachine.github.io/datasprint-toekomsttiendaagse-2025/iiif/2154567f-fd6e-b232-3390-bf19aea349dd/NL-HlmNHA_1478_33848K00_37/canvas/p0/page/anno",
              "type": "Annotation",
              "motivation": "painting",
              "body": {
                "id": "https://maior-images.memorix.nl/ranh/iiif/c58e3217-8446-9d4d-60c8-9e32e6853c9a/full/full/0/default.jpg",
                "type": "Image",
                "height": 4640,
                "width": 6049,
                "service": [
                  {
                    "@id": "https://maior-images.memorix.nl/ranh/iiif/c58e3217-8446-9d4d-60c8-9e32e6853c9a",
                    "@type": "ImageService2",
                    "profile": "http://iiif.io/api/image/2/level2.json"
                  }
                ],
                "format": "image/jpeg"
              },
              "target": "https://amsterdamtimemachine.github.io/datasprint-toekomsttiendaagse-2025/iiif/2154567f-fd6e-b232-3390-bf19aea349dd/NL-HlmNHA_1478_33848K00_37/canvas"
            }
          ]
        }
      ]
    },
    {
      "id": "https://amsterdamtimemachine.github.io/datasprint-toekomsttiendaagse-2025/iiif/2154567f-fd6e-b232-3390-bf19aea349dd/NL-HlmNHA_1478_33848K00_38/canvas",
      "type": "Canvas",
      "label": {
        "nl": [
          "Afscheid heer Bouwmans, adjudant van het Korps Rijkspolitie, AVD steunpunt Badhoevedorp."
        ]
      },
      "height": 4640,
      "width": 6049,
      "metadata": [
        {
          "label": {
            "nl": [
              "URI (Beeldbank)"
            ]
          },
          "value": {
            "nl": [
              "<a href=\"https://hdl.handle.net/21.12102/506b5187-497e-2825-ceb1-b1dc6237314b\">https://hdl.handle.net/21.12102/506b5187-497e-2825-ceb1-b1dc6237314b</a>"
            ]
          }
        }
      ],
      "items": [
        {
          "id": "https://amsterdamtimemachine.github.io/datasprint-toekomsttiendaagse-2025/iiif/2154567f-fd6e-b232-3390-bf19aea349dd/NL-HlmNHA_1478_33848K00_38/canvas/p0/page",
          "type": "AnnotationPage",
          "items": [
            {
              "id": "https://amsterdamtimemachine.github.io/datasprint-toekomsttiendaagse-2025/iiif/2154567f-fd6e-b232-3390-bf19aea349dd/NL-HlmNHA_1478_33848K00_38/canvas/p0/page/anno",
              "type": "Annotation",
              "motivation": "painting",
              "body": {
                "id": "https://maior-images.memorix.nl/ranh/iiif/a8726980-f5b1-0035-4398-1e9091dd9c4a/full/full/0/default.jpg",
                "type": "Image",
                "height": 4640,
                "width": 6049,
                "service": [
                  {
                    "@id": "https://maior-images.memorix.nl/ranh/iiif/a8726980-f5b1-0035-4398-1e9091dd9c4a",
                    "@type": "ImageService2",
                    "profile": "http://iiif.io/api/image/2/level2.json"
                  }
                ],
                "format": "image/jpeg"
              },
              "target": "https://amsterdamtimemachine.github.io/datasprint-toekomsttiendaagse-2025/iiif/2154567f-fd6e-b232-3390-bf19aea349dd/NL-HlmNHA_1478_33848K00_38/canvas"
            }
          ]
        }
      ]
    },
    {
      "id": "https://amsterdamtimemachine.github.io/datasprint-toekomsttiendaagse-2025/iiif/2154567f-fd6e-b232-3390-bf19aea349dd/NL-HlmNHA_1478_33848K00_36/canvas",
      "type": "Canvas",
      "label": {
        "nl": [
          "Afscheid heer Bouwmans, adjudant van het Korps Rijkspolitie, AVD steunpunt Badhoevedorp."
        ]
      },
      "height": 4640,
      "width": 6049,
      "metadata": [
        {
          "label": {
            "nl": [
              "URI (Beeldbank)"
            ]
          },
          "value": {
            "nl": [
              "<a href=\"https://hdl.handle.net/21.12102/9a1b3579-3140-ab49-c1f6-58e3588a607f\">https://hdl.handle.net/21.12102/9a1b3579-3140-ab49-c1f6-58e3588a607f</a>"
            ]
          }
        }
      ],
      "items": [
        {
          "id": "https://amsterdamtimemachine.github.io/datasprint-toekomsttiendaagse-2025/iiif/2154567f-fd6e-b232-3390-bf19aea349dd/NL-HlmNHA_1478_33848K00_36/canvas/p0/page",
          "type": "AnnotationPage",
          "items": [
            {
              "id": "https://amsterdamtimemachine.github.io/datasprint-toekomsttiendaagse-2025/iiif/2154567f-fd6e-b232-3390-bf19aea349dd/NL-HlmNHA_1478_33848K00_36/canvas/p0/page/anno",
              "type": "Annotation",
              "motivation": "painting",
              "body": {
                "id": "https://maior-images.memorix.nl/ranh/iiif/582e9d95-755b-da14-8652-cec1e770f9b5/full/full/0/default.jpg",
                "type": "Image",
                "height": 4640,
                "width": 6049,
                "service": [
                  {
                    "@id": "https://maior-images.memorix.nl/ranh/iiif/582e9d95-755b-da14-8652-cec1e770f9b5",
                    "@type": "ImageService2",
                    "profile": "http://iiif.io/api/image/2/level2.json"
                  }
                ],
                "format": "image/jpeg"
              },
              "target": "https://amsterdamtimemachine.github.io/datasprint-toekomsttiendaagse-2025/iiif/2154567f-fd6e-b232-3390-bf19aea349dd/NL-HlmNHA_1478_33848K00_36/canvas"
            }
          ]
        }
      ]
    }
  ]
}