{
  "@context": [
    "http://iiif.io/api/extension/navplace/context.json",
    "http://iiif.io/api/presentation/3/context.json"
  ],
  "id": "https://amsterdamtimemachine.github.io/datasprint-toekomsttiendaagse-2025/iiif/nha/4e7854fb-d4db-78d0-eef1-0358ea6e0eff.json",
  "type": "Manifest",
  "label": {
    "nl": [
      "Exterieur boerderij De Badhoeve in Badhoevedorp (1980-05-12)"
    ]
  },
  "metadata": [
    {
      "label": {
        "nl": [
          "Titel"
        ]
      },
      "value": {
        "nl": [
          "Exterieur boerderij De Badhoeve in Badhoevedorp"
        ]
      }
    },
    {
      "label": {
        "nl": [
          "Datum"
        ]
      },
      "value": {
        "nl": [
          "1980-05-12"
        ]
      }
    },
    {
      "label": {
        "nl": [
          "Plaats"
        ]
      },
      "value": {
        "nl": [
          "<a href=\"http://www.wikidata.org/entity/Q18978418\">Burgemeester Amersfoordtlaan</a>"
        ]
      }
    },
    {
      "label": {
        "nl": [
          "Concept"
        ]
      },
      "value": {
        "nl": [
          ""
        ]
      }
    },
    {
      "label": {
        "nl": [
          "GTAA"
        ]
      },
      "value": {
        "nl": [
          ""
        ]
      }
    }
  ],
  "navPlace": {
    "type": "FeatureCollection",
    "features": [
      {
        "type": "Feature",
        "geometry": {
          "type": "Point",
          "coordinates": [
            4.7881,
            52.3398
          ]
        },
        "properties": {
          "title": "Burgemeester Amersfoordtlaan",
          "url": "http://www.wikidata.org/entity/Q18978418"
        }
      }
    ]
  },
  "items": [
    {
      "id": "https://amsterdamtimemachine.github.io/datasprint-toekomsttiendaagse-2025/iiif/4e7854fb-d4db-78d0-eef1-0358ea6e0eff/NL-HlmNHA_1478_19326K00_09/canvas",
      "type": "Canvas",
      "label": {
        "nl": [
          "Exterieur boerderij De Badhoeve in Badhoevedorp"
        ]
      },
      "height": 4640,
      "width": 6049,
      "metadata": [
        {
          "label": {
            "nl": [
              "URI (Beeldbank)"
            ]
          },
          "value": {
            "nl": [
              "<a href=\"https://hdl.handle.net/21.12102/29b63fd7-a862-bde2-26c8-af77e637b9d8\">https://hdl.handle.net/21.12102/29b63fd7-a862-bde2-26c8-af77e637b9d8</a>"
            ]
          }
        }
      ],
      "items": [
        {
          "id": "https://amsterdamtimemachine.github.io/datasprint-toekomsttiendaagse-2025/iiif/4e7854fb-d4db-78d0-eef1-0358ea6e0eff/NL-HlmNHA_1478_19326K00_09/canvas/p0/page",
          "type": "AnnotationPage",
          "items": [
            {
              "id": "https://amsterdamtimemachine.github.io/datasprint-toekomsttiendaagse-2025/iiif/4e7854fb-d4db-78d0-eef1-0358ea6e0eff/NL-HlmNHA_1478_19326K00_09/canvas/p0/page/anno",
              "type": "Annotation",
              "motivation": "painting",
              "body": {
                "id": "https://maior-images.memorix.nl/ranh/iiif/e8012c19-2655-cd49-505f-3c906742c6ae/full/full/0/default.jpg",
                "type": "Image",
                "height": 4640,
                "width": 6049,
                "service": [
                  {
                    "@id": "https://maior-images.memorix.nl/ranh/iiif/e8012c19-2655-cd49-505f-3c906742c6ae",
                    "@type": "ImageService2",
                    "profile": "http://iiif.io/api/image/2/level2.json"
                  }
                ],
                "format": "image/jpeg"
              },
              "target": "https://amsterdamtimemachine.github.io/datasprint-toekomsttiendaagse-2025/iiif/4e7854fb-d4db-78d0-eef1-0358ea6e0eff/NL-HlmNHA_1478_19326K00_09/canvas"
            }
          ]
        }
      ]
    },
    {
      "id": "https://amsterdamtimemachine.github.io/datasprint-toekomsttiendaagse-2025/iiif/4e7854fb-d4db-78d0-eef1-0358ea6e0eff/NL-HlmNHA_1478_19326K00_08/canvas",
      "type": "Canvas",
      "label": {
        "nl": [
          "Exterieur boerderij De Badhoeve in Badhoevedorp"
        ]
      },
      "height": 4640,
      "width": 6049,
      "metadata": [
        {
          "label": {
            "nl": [
              "URI (Beeldbank)"
            ]
          },
          "value": {
            "nl": [
              "<a href=\"https://hdl.handle.net/21.12102/4dfdb303-f52a-cd4b-c505-00f77e826511\">https://hdl.handle.net/21.12102/4dfdb303-f52a-cd4b-c505-00f77e826511</a>"
            ]
          }
        }
      ],
      "items": [
        {
          "id": "https://amsterdamtimemachine.github.io/datasprint-toekomsttiendaagse-2025/iiif/4e7854fb-d4db-78d0-eef1-0358ea6e0eff/NL-HlmNHA_1478_19326K00_08/canvas/p0/page",
          "type": "AnnotationPage",
          "items": [
            {
              "id": "https://amsterdamtimemachine.github.io/datasprint-toekomsttiendaagse-2025/iiif/4e7854fb-d4db-78d0-eef1-0358ea6e0eff/NL-HlmNHA_1478_19326K00_08/canvas/p0/page/anno",
              "type": "Annotation",
              "motivation": "painting",
              "body": {
                "id": "https://maior-images.memorix.nl/ranh/iiif/c8be03cb-8d32-9e73-15f3-f9904b2f410c/full/full/0/default.jpg",
                "type": "Image",
                "height": 4640,
                "width": 6049,
                "service": [
                  {
                    "@id": "https://maior-images.memorix.nl/ranh/iiif/c8be03cb-8d32-9e73-15f3-f9904b2f410c",
                    "@type": "ImageService2",
                    "profile": "http://iiif.io/api/image/2/level2.json"
                  }
                ],
                "format": "image/jpeg"
              },
              "target": "https://amsterdamtimemachine.github.io/datasprint-toekomsttiendaagse-2025/iiif/4e7854fb-d4db-78d0-eef1-0358ea6e0eff/NL-HlmNHA_1478_19326K00_08/canvas"
            }
          ]
        }
      ]
    },
    {
      "id": "https://amsterdamtimemachine.github.io/datasprint-toekomsttiendaagse-2025/iiif/4e7854fb-d4db-78d0-eef1-0358ea6e0eff/NL-HlmNHA_1478_19326K00_11/canvas",
      "type": "Canvas",
      "label": {
        "nl": [
          "Exterieur boerderij De Badhoeve in Badhoevedorp"
        ]
      },
      "height": 4640,
      "width": 6049,
      "metadata": [
        {
          "label": {
            "nl": [
              "URI (Beeldbank)"
            ]
          },
          "value": {
            "nl": [
              "<a href=\"https://hdl.handle.net/21.12102/f56347e8-e385-6448-cfc8-d1053e5dd0fb\">https://hdl.handle.net/21.12102/f56347e8-e385-6448-cfc8-d1053e5dd0fb</a>"
            ]
          }
        }
      ],
      "items": [
        {
          "id": "https://amsterdamtimemachine.github.io/datasprint-toekomsttiendaagse-2025/iiif/4e7854fb-d4db-78d0-eef1-0358ea6e0eff/NL-HlmNHA_1478_19326K00_11/canvas/p0/page",
          "type": "AnnotationPage",
          "items": [
            {
              "id": "https://amsterdamtimemachine.github.io/datasprint-toekomsttiendaagse-2025/iiif/4e7854fb-d4db-78d0-eef1-0358ea6e0eff/NL-HlmNHA_1478_19326K00_11/canvas/p0/page/anno",
              "type": "Annotation",
              "motivation": "painting",
              "body": {
                "id": "https://maior-images.memorix.nl/ranh/iiif/e01b6437-c18c-93b6-5ce1-07380f4cad9d/full/full/0/default.jpg",
                "type": "Image",
                "height": 4640,
                "width": 6049,
                "service": [
                  {
                    "@id": "https://maior-images.memorix.nl/ranh/iiif/e01b6437-c18c-93b6-5ce1-07380f4cad9d",
                    "@type": "ImageService2",
                    "profile": "http://iiif.io/api/image/2/level2.json"
                  }
                ],
                "format": "image/jpeg"
              },
              "target": "https://amsterdamtimemachine.github.io/datasprint-toekomsttiendaagse-2025/iiif/4e7854fb-d4db-78d0-eef1-0358ea6e0eff/NL-HlmNHA_1478_19326K00_11/canvas"
            }
          ]
        }
      ]
    },
    {
      "id": "https://amsterdamtimemachine.github.io/datasprint-toekomsttiendaagse-2025/iiif/4e7854fb-d4db-78d0-eef1-0358ea6e0eff/NL-HlmNHA_1478_19326K00_10/canvas",
      "type": "Canvas",
      "label": {
        "nl": [
          "Exterieur boerderij De Badhoeve in Badhoevedorp"
        ]
      },
      "height": 4640,
      "width": 6049,
      "metadata": [
        {
          "label": {
            "nl": [
              "URI (Beeldbank)"
            ]
          },
          "value": {
            "nl": [
              "<a href=\"https://hdl.handle.net/21.12102/fe45dfef-4e28-5c5a-93ec-6b8ede5e66b2\">https://hdl.handle.net/21.12102/fe45dfef-4e28-5c5a-93ec-6b8ede5e66b2</a>"
            ]
          }
        }
      ],
      "items": [
        {
          "id": "https://amsterdamtimemachine.github.io/datasprint-toekomsttiendaagse-2025/iiif/4e7854fb-d4db-78d0-eef1-0358ea6e0eff/NL-HlmNHA_1478_19326K00_10/canvas/p0/page",
          "type": "AnnotationPage",
          "items": [
            {
              "id": "https://amsterdamtimemachine.github.io/datasprint-toekomsttiendaagse-2025/iiif/4e7854fb-d4db-78d0-eef1-0358ea6e0eff/NL-HlmNHA_1478_19326K00_10/canvas/p0/page/anno",
              "type": "Annotation",
              "motivation": "painting",
              "body": {
                "id": "https://maior-images.memorix.nl/ranh/iiif/dc55ec56-aa57-7ac6-4e95-73ada082cc9e/full/full/0/default.jpg",
                "type": "Image",
                "height": 4640,
                "width": 6049,
                "service": [
                  {
                    "@id": "https://maior-images.memorix.nl/ranh/iiif/dc55ec56-aa57-7ac6-4e95-73ada082cc9e",
                    "@type": "ImageService2",
                    "profile": "http://iiif.io/api/image/2/level2.json"
                  }
                ],
                "format": "image/jpeg"
              },
              "target": "https://amsterdamtimemachine.github.io/datasprint-toekomsttiendaagse-2025/iiif/4e7854fb-d4db-78d0-eef1-0358ea6e0eff/NL-HlmNHA_1478_19326K00_10/canvas"
            }
          ]
        }
      ]
    }
  ]
}