{
  "@context": [
    "http://iiif.io/api/extension/navplace/context.json",
    "http://iiif.io/api/presentation/3/context.json"
  ],
  "id": "https://amsterdamtimemachine.github.io/datasprint-toekomsttiendaagse-2025/iiif/nha/f5257a2d-f18b-f702-d974-ea70c328cc4b.json",
  "type": "Manifest",
  "label": {
    "nl": [
      "Beschilderde muur bij Hilton, Schiphol (1985-08-05)"
    ]
  },
  "metadata": [
    {
      "label": {
        "nl": [
          "Titel"
        ]
      },
      "value": {
        "nl": [
          "Beschilderde muur bij Hilton, Schiphol"
        ]
      }
    },
    {
      "label": {
        "nl": [
          "Datum"
        ]
      },
      "value": {
        "nl": [
          "1985-08-05"
        ]
      }
    },
    {
      "label": {
        "nl": [
          "Plaats"
        ]
      },
      "value": {
        "nl": [
          "<a href=\"http://www.wikidata.org/entity/Q9694\">Luchthaven Schiphol</a>"
        ]
      }
    },
    {
      "label": {
        "nl": [
          "Concept"
        ]
      },
      "value": {
        "nl": [
          "Muren"
        ]
      }
    },
    {
      "label": {
        "nl": [
          "GTAA"
        ]
      },
      "value": {
        "nl": [
          "http://data.beeldengeluid.nl/gtaa/26347"
        ]
      }
    }
  ],
  "navPlace": {
    "type": "FeatureCollection",
    "features": [
      {
        "type": "Feature",
        "geometry": {
          "type": "Point",
          "coordinates": [
            4.764169,
            52.3081
          ]
        },
        "properties": {
          "title": "Luchthaven Schiphol",
          "url": "http://www.wikidata.org/entity/Q9694"
        }
      }
    ]
  },
  "items": [
    {
      "id": "https://amsterdamtimemachine.github.io/datasprint-toekomsttiendaagse-2025/iiif/f5257a2d-f18b-f702-d974-ea70c328cc4b/NL-HlmNHA_1478_25392K00_24/canvas",
      "type": "Canvas",
      "label": {
        "nl": [
          "Beschilderde muur bij Hilton, Schiphol"
        ]
      },
      "height": 4640,
      "width": 6049,
      "metadata": [
        {
          "label": {
            "nl": [
              "URI (Beeldbank)"
            ]
          },
          "value": {
            "nl": [
              "<a href=\"https://hdl.handle.net/21.12102/3d00c93f-6343-096e-7e2a-36ddc255bb4a\">https://hdl.handle.net/21.12102/3d00c93f-6343-096e-7e2a-36ddc255bb4a</a>"
            ]
          }
        }
      ],
      "items": [
        {
          "id": "https://amsterdamtimemachine.github.io/datasprint-toekomsttiendaagse-2025/iiif/f5257a2d-f18b-f702-d974-ea70c328cc4b/NL-HlmNHA_1478_25392K00_24/canvas/p0/page",
          "type": "AnnotationPage",
          "items": [
            {
              "id": "https://amsterdamtimemachine.github.io/datasprint-toekomsttiendaagse-2025/iiif/f5257a2d-f18b-f702-d974-ea70c328cc4b/NL-HlmNHA_1478_25392K00_24/canvas/p0/page/anno",
              "type": "Annotation",
              "motivation": "painting",
              "body": {
                "id": "https://maior-images.memorix.nl/ranh/iiif/71e9d4c8-3e8e-db13-cecf-6b1f72906d0f/full/full/0/default.jpg",
                "type": "Image",
                "height": 4640,
                "width": 6049,
                "service": [
                  {
                    "@id": "https://maior-images.memorix.nl/ranh/iiif/71e9d4c8-3e8e-db13-cecf-6b1f72906d0f",
                    "@type": "ImageService2",
                    "profile": "http://iiif.io/api/image/2/level2.json"
                  }
                ],
                "format": "image/jpeg"
              },
              "target": "https://amsterdamtimemachine.github.io/datasprint-toekomsttiendaagse-2025/iiif/f5257a2d-f18b-f702-d974-ea70c328cc4b/NL-HlmNHA_1478_25392K00_24/canvas"
            }
          ]
        }
      ]
    },
    {
      "id": "https://amsterdamtimemachine.github.io/datasprint-toekomsttiendaagse-2025/iiif/f5257a2d-f18b-f702-d974-ea70c328cc4b/NL-HlmNHA_1478_25392K00_21/canvas",
      "type": "Canvas",
      "label": {
        "nl": [
          "Beschilderde muur bij Hilton, Schiphol"
        ]
      },
      "height": 4640,
      "width": 6049,
      "metadata": [
        {
          "label": {
            "nl": [
              "URI (Beeldbank)"
            ]
          },
          "value": {
            "nl": [
              "<a href=\"https://hdl.handle.net/21.12102/4bcd0ca1-6eb4-9f35-fba2-472cbecf2924\">https://hdl.handle.net/21.12102/4bcd0ca1-6eb4-9f35-fba2-472cbecf2924</a>"
            ]
          }
        }
      ],
      "items": [
        {
          "id": "https://amsterdamtimemachine.github.io/datasprint-toekomsttiendaagse-2025/iiif/f5257a2d-f18b-f702-d974-ea70c328cc4b/NL-HlmNHA_1478_25392K00_21/canvas/p0/page",
          "type": "AnnotationPage",
          "items": [
            {
              "id": "https://amsterdamtimemachine.github.io/datasprint-toekomsttiendaagse-2025/iiif/f5257a2d-f18b-f702-d974-ea70c328cc4b/NL-HlmNHA_1478_25392K00_21/canvas/p0/page/anno",
              "type": "Annotation",
              "motivation": "painting",
              "body": {
                "id": "https://maior-images.memorix.nl/ranh/iiif/d2a74526-33a0-4388-2b14-986a453831bf/full/full/0/default.jpg",
                "type": "Image",
                "height": 4640,
                "width": 6049,
                "service": [
                  {
                    "@id": "https://maior-images.memorix.nl/ranh/iiif/d2a74526-33a0-4388-2b14-986a453831bf",
                    "@type": "ImageService2",
                    "profile": "http://iiif.io/api/image/2/level2.json"
                  }
                ],
                "format": "image/jpeg"
              },
              "target": "https://amsterdamtimemachine.github.io/datasprint-toekomsttiendaagse-2025/iiif/f5257a2d-f18b-f702-d974-ea70c328cc4b/NL-HlmNHA_1478_25392K00_21/canvas"
            }
          ]
        }
      ]
    },
    {
      "id": "https://amsterdamtimemachine.github.io/datasprint-toekomsttiendaagse-2025/iiif/f5257a2d-f18b-f702-d974-ea70c328cc4b/NL-HlmNHA_1478_25392K00_22/canvas",
      "type": "Canvas",
      "label": {
        "nl": [
          "Beschilderde muur bij Hilton, Schiphol"
        ]
      },
      "height": 4640,
      "width": 6049,
      "metadata": [
        {
          "label": {
            "nl": [
              "URI (Beeldbank)"
            ]
          },
          "value": {
            "nl": [
              "<a href=\"https://hdl.handle.net/21.12102/4c4efb23-4329-f704-9bd0-a19b8b808305\">https://hdl.handle.net/21.12102/4c4efb23-4329-f704-9bd0-a19b8b808305</a>"
            ]
          }
        }
      ],
      "items": [
        {
          "id": "https://amsterdamtimemachine.github.io/datasprint-toekomsttiendaagse-2025/iiif/f5257a2d-f18b-f702-d974-ea70c328cc4b/NL-HlmNHA_1478_25392K00_22/canvas/p0/page",
          "type": "AnnotationPage",
          "items": [
            {
              "id": "https://amsterdamtimemachine.github.io/datasprint-toekomsttiendaagse-2025/iiif/f5257a2d-f18b-f702-d974-ea70c328cc4b/NL-HlmNHA_1478_25392K00_22/canvas/p0/page/anno",
              "type": "Annotation",
              "motivation": "painting",
              "body": {
                "id": "https://maior-images.memorix.nl/ranh/iiif/149d6a6e-8431-6e72-3e33-3597dbe6f724/full/full/0/default.jpg",
                "type": "Image",
                "height": 4640,
                "width": 6049,
                "service": [
                  {
                    "@id": "https://maior-images.memorix.nl/ranh/iiif/149d6a6e-8431-6e72-3e33-3597dbe6f724",
                    "@type": "ImageService2",
                    "profile": "http://iiif.io/api/image/2/level2.json"
                  }
                ],
                "format": "image/jpeg"
              },
              "target": "https://amsterdamtimemachine.github.io/datasprint-toekomsttiendaagse-2025/iiif/f5257a2d-f18b-f702-d974-ea70c328cc4b/NL-HlmNHA_1478_25392K00_22/canvas"
            }
          ]
        }
      ]
    },
    {
      "id": "https://amsterdamtimemachine.github.io/datasprint-toekomsttiendaagse-2025/iiif/f5257a2d-f18b-f702-d974-ea70c328cc4b/NL-HlmNHA_1478_25392K00_23/canvas",
      "type": "Canvas",
      "label": {
        "nl": [
          "Beschilderde muur bij Hilton, Schiphol"
        ]
      },
      "height": 4640,
      "width": 6049,
      "metadata": [
        {
          "label": {
            "nl": [
              "URI (Beeldbank)"
            ]
          },
          "value": {
            "nl": [
              "<a href=\"https://hdl.handle.net/21.12102/ae3e4efc-9075-94da-ae8a-3645053a6264\">https://hdl.handle.net/21.12102/ae3e4efc-9075-94da-ae8a-3645053a6264</a>"
            ]
          }
        }
      ],
      "items": [
        {
          "id": "https://amsterdamtimemachine.github.io/datasprint-toekomsttiendaagse-2025/iiif/f5257a2d-f18b-f702-d974-ea70c328cc4b/NL-HlmNHA_1478_25392K00_23/canvas/p0/page",
          "type": "AnnotationPage",
          "items": [
            {
              "id": "https://amsterdamtimemachine.github.io/datasprint-toekomsttiendaagse-2025/iiif/f5257a2d-f18b-f702-d974-ea70c328cc4b/NL-HlmNHA_1478_25392K00_23/canvas/p0/page/anno",
              "type": "Annotation",
              "motivation": "painting",
              "body": {
                "id": "https://maior-images.memorix.nl/ranh/iiif/34440705-c137-7494-f112-ede468cf273f/full/full/0/default.jpg",
                "type": "Image",
                "height": 4640,
                "width": 6049,
                "service": [
                  {
                    "@id": "https://maior-images.memorix.nl/ranh/iiif/34440705-c137-7494-f112-ede468cf273f",
                    "@type": "ImageService2",
                    "profile": "http://iiif.io/api/image/2/level2.json"
                  }
                ],
                "format": "image/jpeg"
              },
              "target": "https://amsterdamtimemachine.github.io/datasprint-toekomsttiendaagse-2025/iiif/f5257a2d-f18b-f702-d974-ea70c328cc4b/NL-HlmNHA_1478_25392K00_23/canvas"
            }
          ]
        }
      ]
    },
    {
      "id": "https://amsterdamtimemachine.github.io/datasprint-toekomsttiendaagse-2025/iiif/f5257a2d-f18b-f702-d974-ea70c328cc4b/NL-HlmNHA_1478_25392K00_20/canvas",
      "type": "Canvas",
      "label": {
        "nl": [
          "Beschilderde muur bij Hilton, Schiphol"
        ]
      },
      "height": 4640,
      "width": 6049,
      "metadata": [
        {
          "label": {
            "nl": [
              "URI (Beeldbank)"
            ]
          },
          "value": {
            "nl": [
              "<a href=\"https://hdl.handle.net/21.12102/faed2c7b-7149-acfe-164b-732d3c62206a\">https://hdl.handle.net/21.12102/faed2c7b-7149-acfe-164b-732d3c62206a</a>"
            ]
          }
        }
      ],
      "items": [
        {
          "id": "https://amsterdamtimemachine.github.io/datasprint-toekomsttiendaagse-2025/iiif/f5257a2d-f18b-f702-d974-ea70c328cc4b/NL-HlmNHA_1478_25392K00_20/canvas/p0/page",
          "type": "AnnotationPage",
          "items": [
            {
              "id": "https://amsterdamtimemachine.github.io/datasprint-toekomsttiendaagse-2025/iiif/f5257a2d-f18b-f702-d974-ea70c328cc4b/NL-HlmNHA_1478_25392K00_20/canvas/p0/page/anno",
              "type": "Annotation",
              "motivation": "painting",
              "body": {
                "id": "https://maior-images.memorix.nl/ranh/iiif/348103ad-add4-0e82-c59d-8810ef301bb9/full/full/0/default.jpg",
                "type": "Image",
                "height": 4640,
                "width": 6049,
                "service": [
                  {
                    "@id": "https://maior-images.memorix.nl/ranh/iiif/348103ad-add4-0e82-c59d-8810ef301bb9",
                    "@type": "ImageService2",
                    "profile": "http://iiif.io/api/image/2/level2.json"
                  }
                ],
                "format": "image/jpeg"
              },
              "target": "https://amsterdamtimemachine.github.io/datasprint-toekomsttiendaagse-2025/iiif/f5257a2d-f18b-f702-d974-ea70c328cc4b/NL-HlmNHA_1478_25392K00_20/canvas"
            }
          ]
        }
      ]
    }
  ]
}